cpg_aggregation/__init__.py
cpg_aggregation/aggregations.py
cpg_aggregation-1.0.0.dist-info/licenses/LICENSE
cpg_aggregation-1.0.0.dist-info/METADATA
cpg_aggregation-1.0.0.dist-info/WHEEL
cpg_aggregation-1.0.0.dist-info/top_level.txt
cpg_aggregation-1.0.0.dist-info/RECORD
