Metadata-Version: 2.4
Name: cpg_aggregation
Version: 1.0.0
Summary: Gold layer aggregation functions for Cholayil CPG Data Warehouse in Snowflake
Author-email: Akash <your.email@example.com>
Maintainer-email: Akash <your.email@example.com>
License: MIT
Project-URL: Homepage, https://github.com/yourusername/cholayil-gold-aggregations
Project-URL: Documentation, https://github.com/yourusername/cholayil-gold-aggregations#readme
Project-URL: Repository, https://github.com/yourusername/cholayil-gold-aggregations.git
Project-URL: Issues, https://github.com/yourusername/cholayil-gold-aggregations/issues
Keywords: snowflake,data-warehouse,etl,cpg,analytics,gold-layer,aggregations
Classifier: Development Status :: 4 - Beta
Classifier: Intended Audience :: Developers
Classifier: Intended Audience :: Science/Research
Classifier: License :: OSI Approved :: MIT License
Classifier: Operating System :: OS Independent
Classifier: Programming Language :: Python :: 3
Classifier: Programming Language :: Python :: 3.8
Classifier: Programming Language :: Python :: 3.9
Classifier: Programming Language :: Python :: 3.10
Classifier: Programming Language :: Python :: 3.11
Classifier: Topic :: Database
Classifier: Topic :: Scientific/Engineering :: Information Analysis
Requires-Python: >=3.8
License-File: LICENSE
Requires-Dist: snowflake-snowpark-python>=1.0.0
Provides-Extra: dev
Requires-Dist: pytest>=7.0.0; extra == "dev"
Requires-Dist: pytest-cov>=4.0.0; extra == "dev"
Requires-Dist: black>=23.0.0; extra == "dev"
Requires-Dist: flake8>=6.0.0; extra == "dev"
Requires-Dist: mypy>=1.0.0; extra == "dev"
Dynamic: license-file
